nama_alamat/__init__.py
nama_alamat/nama_alamat.py
nama_alamat/preprocessing/__init__.py
nama_alamat/preprocessing/preprocessing.py
nama_alamat/preprocessing/dict_files/__init__.py
nama_alamat-0.3.4.dist-info/LICENSE
nama_alamat-0.3.4.dist-info/METADATA
nama_alamat-0.3.4.dist-info/WHEEL
nama_alamat-0.3.4.dist-info/entry_points.txt
nama_alamat-0.3.4.dist-info/top_level.txt
nama_alamat-0.3.4.dist-info/RECORD
